azcam_console/__init__.py
azcam_console/console.py
azcam_console/console_mock.py
azcam_console/database_console.py
azcam_console/parameters_console.py
azcam_console/plot.py
azcam_console/shortcuts.py
azcam_console/utils.py
azcam_console/scripts/__init__.py
azcam_console/scripts/centroids.py
azcam_console/scripts/check_bits.py
azcam_console/scripts/display_files.py
azcam_console/scripts/exposure_timer.py
azcam_console/scripts/get_pressures.py
azcam_console/scripts/get_temperatures.py
azcam_console/scripts/plot_header_times.py
azcam_console/scripts/plot_images.py
azcam_console/scripts/plot_keywords.py
azcam_console/scripts/plot_log_temps.py
azcam_console/scripts/readnoise_correction.py
azcam_console/scripts/scan_wavelengths.py
azcam_console/scripts/show_histogram.py
azcam_console/scripts/show_sequence_keywords.py
azcam_console/scripts/show_sequence_stats.py
azcam_console/scripts/test_communications.py
azcam_console/scripts/test_console.py
azcam_console/scripts/test_controller.py
azcam_console/scripts/test_exposures.py
azcam_console/scripts/test_filters.py
azcam_console/scripts/test_gain_stability.py
azcam_console/scripts/test_reset.py
azcam_console/scripts/test_shutter.py
azcam_console/scripts/test_temperatures.py
azcam_console/scripts/test_wavelengths.py
azcam_console/scripts/threshold_image.py
azcam_console/tools/__init__.py
azcam_console/tools/console_arc.py
azcam_console/tools/console_archon.py
azcam_console/tools/console_tools.py
azcam_console/tools/controller.py
azcam_console/tools/display.py
azcam_console/tools/ds9display.py
azcam_console/tools/exposure.py
azcam_console/tools/focus.py
azcam_console/tools/instrument.py
azcam_console/tools/telescope.py
azcam_console/tools/tempcon.py
azcam_console-24.0.dist-info/LICENSE
azcam_console-24.0.dist-info/WHEEL
azcam_console-24.0.dist-info/METADATA
azcam_console-24.0.dist-info/RECORD
