Metadata-Version: 2.1
Name: azcam-console
Version: 24.0
Summary: Console package for the AzCam acquisition and analysis package
Keywords: ccd,imaging,astronomy,sensors
Author: Michael Lesser
Author-email: mlesser@arizona.edu
Requires-Python: >= 3.10
Requires-Dist: numpy
Requires-Dist: matplotlib
Project-URL: Documentation, https://azcam.readthedocs.io/
Project-URL: Repository, https://github.com/mplesser/azcam-console/
